landmarkerioserver
