Metadata-Version: 1.1
Name: landmarkerio-server
Version: 0.0.6
Summary: Menpo-based server for www.landmarker.io
Home-page: https://github.com/menpo/landmarkerio-server/
Author: James Booth
Author-email: james.booth08@imperial.ac.uk
License: UNKNOWN
Platform: UNKNOWN
Classifier: Development Status :: 3 - Alpha
Classifier: Intended Audience :: Developers
Classifier: Intended Audience :: Science/Research
Classifier: License :: OSI Approved :: BSD License
Classifier: Operating System :: OS Independent
Classifier: Programming Language :: Python :: 2
Classifier: Programming Language :: Python :: 2.7
